MANIFEST.in
README.rst
setup.py
docs/HISTORY.txt
docs/LICENSE.GPL
docs/LICENSE.txt
docs/examples/an.png
docs/examples/ct.png
docs/examples/pi.png
ftw/__init__.py
ftw.avatar.egg-info/PKG-INFO
ftw.avatar.egg-info/SOURCES.txt
ftw.avatar.egg-info/dependency_links.txt
ftw.avatar.egg-info/entry_points.txt
ftw.avatar.egg-info/namespace_packages.txt
ftw.avatar.egg-info/not-zip-safe
ftw.avatar.egg-info/requires.txt
ftw.avatar.egg-info/top_level.txt
ftw/avatar/__init__.py
ftw/avatar/configure.zcml
ftw/avatar/default.py
ftw/avatar/handlers.py
ftw/avatar/interfaces.py
ftw/avatar/member.py
ftw/avatar/patches.py
ftw/avatar/testing.py
ftw/avatar/utils.py
ftw/avatar/browser/__init__.py
ftw/avatar/browser/configure.zcml
ftw/avatar/browser/portrait.py
ftw/avatar/font/FantasqueSansMono-Bold.ttf
ftw/avatar/font/OFL.txt
ftw/avatar/font/README.md
ftw/avatar/tests/__init__.py
ftw/avatar/tests/test_avatar_scale_patch.py
ftw/avatar/tests/test_default_generator.py
ftw/avatar/tests/test_default_utility.py
ftw/avatar/tests/test_generates_avatars.py
ftw/avatar/tests/test_member.py
ftw/avatar/tests/test_portrait_scaling_view.py