Metadata-Version: 2.1
Name: ftw.avatar
Version: 2.1.0
Summary: Generates a personal default avatar for new Plone users
Home-page: https://github.com/4teamwork/ftw.avatar
Author: 4teamwork AG
Author-email: mailto:info@4teamwork.ch
License: GPL2
Keywords: ftw avatar personal user portrait plone
Platform: UNKNOWN
Classifier: Framework :: Plone
Classifier: Framework :: Plone :: 4.2
Classifier: Framework :: Plone :: 4.3
Classifier: Intended Audience :: Developers
Classifier: Topic :: Software Development :: Libraries :: Python Modules
Provides-Extra: tests
